kploy.py
kploycommon.py
setup.py
kploy.egg-info/PKG-INFO
kploy.egg-info/SOURCES.txt
kploy.egg-info/dependency_links.txt
kploy.egg-info/entry_points.txt
kploy.egg-info/not-zip-safe
kploy.egg-info/requires.txt
kploy.egg-info/top_level.txt