Metadata-Version: 1.1
Name: kploy
Version: 0.10.1
Summary: An opinionated Kubernetes deployment system for appops
Home-page: https://github.com/kubernauts/kploy
Author: Michael Hausenblas
Author-email: michael.hausenblas@gmail.com
License: Apache
Keywords: Kubernetes,containers,appops,deployment
Platform: UNKNOWN
Classifier: Development Status :: 3 - Alpha
Classifier: Environment :: Web Environment
Classifier: Intended Audience :: Developers
Classifier: License :: OSI Approved :: Apache Software License
Classifier: Operating System :: OS Independent
Classifier: Programming Language :: Python
